fastbin/__init__.py
fastbin/enforcer.py
fastbin/policy.py
fastbin/py.typed
fastbin-1.0.0.dist-info/LICENSE.md
fastbin-1.0.0.dist-info/WHEEL
fastbin-1.0.0.dist-info/METADATA
fastbin-1.0.0.dist-info/RECORD
