Metadata-Version: 2.1
Name: fastbin
Version: 1.0.0
Summary: Performance orientated improvements to pycasbin
Home-page: https://github.com/wakemaster39/fastbin
License: MIT
Keywords: casbin,authorization
Author: Cameron Hurst
Author-email: cameron.a.hurst@gmail.com
Requires-Python: >=3.6.2,<4.0.0
Classifier: License :: OSI Approved :: MIT License
Classifier: Programming Language :: Python :: 3
Classifier: Programming Language :: Python :: 3.7
Classifier: Programming Language :: Python :: 3.8
Classifier: Programming Language :: Python :: 3.9
Requires-Dist: casbin (>=1.4.0,<2.0.0)
Project-URL: Repository, https://github.com/wakemaster39/fastbin
